Metadata-Version: 2.1
Name: scarletdb
Version: 0.4
Summary: Light document database.
Home-page: https://github.com/xd-pro/scarletdb
Author: Finnbar McC
Author-email: xfinnbar@gmail.com
License: MIT
Download-URL: https://github.com/Xd-pro/ScarletDB/archive/refs/tags/0.1-beta.tar.gz
Keywords: db,database,scarlet
Platform: UNKNOWN
Classifier: Development Status :: 4 - Beta
Classifier: Intended Audience :: Developers
Classifier: Topic :: Software Development :: Build Tools
Classifier: License :: OSI Approved :: MIT License
Classifier: Programming Language :: Python :: 3.8
